aisy_database/__init__.py
aisy_database/db_delete.py
aisy_database/db_save.py
aisy_database/db_select.py
aisy_database/db_tables.py
aisy_database/db_update.py
tests/__init__.py
aisy_database-0.2.0.dist-info/LICENSE
aisy_database-0.2.0.dist-info/METADATA
aisy_database-0.2.0.dist-info/WHEEL
aisy_database-0.2.0.dist-info/top_level.txt
aisy_database-0.2.0.dist-info/RECORD
