Metadata-Version: 2.1
Name: aisy-database
Version: 0.2.0
Summary: Database Package for AISY Framework
Home-page: https://aisylab.github.io/AISY_docs/
Author: Guilherme Perin
Author-email: guilhermeperin7@gmail.com
License: UNKNOWN
Keywords: side-channel analysis deep learning profiled attacks
Platform: UNKNOWN
Classifier: Programming Language :: Python :: 3
Classifier: License :: OSI Approved :: MIT License
Classifier: Operating System :: OS Independent
License-File: LICENSE
